Src/Madule02/checkprime.py
Src/Madule02/filterodd.py
Src/Madule02/removeconsonants.py
Src/Madule02/swaping.py
Src/Module01/AreaOfShapes.py
Src/Module01/LCM.py
Src/Module01/lamdacalc.py
ttqa_one-0.0.1.dist-info/LICENSE
ttqa_one-0.0.1.dist-info/METADATA
ttqa_one-0.0.1.dist-info/WHEEL
ttqa_one-0.0.1.dist-info/top_level.txt
ttqa_one-0.0.1.dist-info/RECORD
