Metadata-Version: 2.1
Name: ttqa_one
Version: 0.0.1
Summary: A pakage that contains some math functions and other functions
Author-email: Shan ul Haq Zafar <msdsf22m014@pucit.edu.pk>
Project-URL: Homepage, https://github.com/MSDSF22M014/TTQ_A1.git
Project-URL: Bug Tracker, https://github.com/MSDSF22M014/TTQ_A1.git/issues
Classifier: Programming Language :: Python :: 3
Classifier: License :: OSI Approved :: MIT License
Classifier: Operating System :: OS Independent
Requires-Python: >=3.7
License-File: LICENSE
